CHANGELOG.rst
LICENSE.txt
MANIFEST.in
README.rst
requirements.dev.txt
requirements.txt
setup.cfg
setup.py
bin/oauth2create
bin/oauth2get
oauth2token/__init__.py
oauth2token/app_creds.py
oauth2token/token_mgmt.py
oauth2token.egg-info/PKG-INFO
oauth2token.egg-info/SOURCES.txt
oauth2token.egg-info/dependency_links.txt
oauth2token.egg-info/requires.txt
oauth2token.egg-info/top_level.txt