Metadata-Version: 2.1
Name: oauth2token
Version: 0.0.3
Summary: Oauth2 token management for cli applications
Home-page: https://github.com/VannTen/oauth2token
Author: VannTen
Author-email: mg@max.gautier.name
License: UNKNOWN
Platform: UNKNOWN
Classifier: Programming Language :: Python :: 3
Classifier: License :: OSI Approved :: GNU General Public License v3 (GPLv3)
Classifier: Operating System :: POSIX :: Linux
Classifier: Intended Audience :: End Users/Desktop
Classifier: Development Status :: 2 - Pre-Alpha
Requires-Python: >=3.6
License-File: LICENSE.txt
